scriber/__init__.py
scriber/document.py
scriber/pdf.py
scriber/settings.py
scriber/ui.py
scriber/components/layout.py
scriber/core/nodes.py
scriber/renderers/reportlab/__init__.py
scriber/renderers/reportlab/base.py
scriber/renderers/reportlab/dispatch.py
scriber/renderers/reportlab/handlers/badge.py
scriber/renderers/reportlab/handlers/button.py
scriber/renderers/reportlab/handlers/card.py
scriber/renderers/reportlab/handlers/document.py
scriber/renderers/reportlab/handlers/figure.py
scriber/renderers/reportlab/handlers/image.py
scriber/renderers/reportlab/handlers/layout.py
scriber/renderers/reportlab/handlers/table.py
scriber/renderers/reportlab/handlers/typography.py
scriber/theme/tokens.py
scriber_pdf-0.1.0.dist-info/METADATA
scriber_pdf-0.1.0.dist-info/WHEEL
scriber_pdf-0.1.0.dist-info/RECORD
