Metadata-Version: 2.4
Name: scriber-pdf
Version: 0.1.0
Summary: Build PDFs in Python easily using a component-based structure.
Project-URL: Homepage, https://example.com/
Author: Fabian Serrano
License: Proprietary
Requires-Python: >=3.10
Requires-Dist: reportlab>=3.6
Provides-Extra: images
Requires-Dist: requests>=2.32; extra == 'images'
